questdb_rest/__init__.py
questdb_rest/cli.py
questdb_rest/qdb_canned_queries_pypika.py
questdb_rest/qdb_dukascopy_instruments_search.py
questdb_rest/qdb_gen_random_data.py
questdb_rest/qdb_tv_symbols_search.py
questdb_rest/questdb_table_names_pypika.py
questdb_rest/utils.py
questdb_api-4.5.0.data/scripts/qdb-table-names
questdb_api-4.5.0.data/scripts/qdb-cols
questdb_api-4.5.0.data/scripts/qdb-canned-queries-fzf
questdb_api-4.5.0.data/scripts/qdb-drop-tables-by-regex
questdb_api-4.5.0.data/scripts/qdb-imp-from-stdin
questdb_api-4.5.0.data/scripts/qdb-copy-single-col-values-from-query
questdb_api-4.5.0.data/scripts/qdb-get-single-col-values-from-query
questdb_api-4.5.0.dist-info/LICENSE
questdb_api-4.5.0.dist-info/METADATA
questdb_api-4.5.0.dist-info/WHEEL
questdb_api-4.5.0.dist-info/entry_points.txt
questdb_api-4.5.0.dist-info/RECORD
